README.rst
setup.cfg
setup.py
./__init__.py
./party.py
./transaction.py
./transaction.xml
./tryton.cfg
./locale/de_DE.po
./tests/__init__.py
./tests/test_transaction.py
./view/gateway_form.xml
./view/party_form.xml
./view/payment_profile_form.xml
fio_payment_gateway_authorize_net.egg-info/PKG-INFO
fio_payment_gateway_authorize_net.egg-info/SOURCES.txt
fio_payment_gateway_authorize_net.egg-info/dependency_links.txt
fio_payment_gateway_authorize_net.egg-info/entry_points.txt
fio_payment_gateway_authorize_net.egg-info/not-zip-safe
fio_payment_gateway_authorize_net.egg-info/requires.txt
fio_payment_gateway_authorize_net.egg-info/top_level.txt